PySimpleGUIWeb/PySimpleGUIWeb.py
PySimpleGUIWeb/__init__.py
PySimpleGUIWeb-0.39.0.dist-info/METADATA
PySimpleGUIWeb-0.39.0.dist-info/WHEEL
PySimpleGUIWeb-0.39.0.dist-info/top_level.txt
PySimpleGUIWeb-0.39.0.dist-info/RECORD
