Metadata-Version: 2.1
Name: PySimpleGUIWeb
Version: 0.39.0
Summary: A port of PySimpleGUI that runs in a web browser.  Utilizes Remi as the GUI framework
Home-page: https://github.com/PySimpleGUI/PySimpleGUI
Author: PySimpleGUI
Author-email: PySimpleGUI@PySimpleGUI.org
License: UNKNOWN
Keywords: GUI UI Remi tkinter wrapper simple easy beginner novice student graphics progressbar progressmeter
Platform: UNKNOWN
Classifier: Programming Language :: Python :: 3
Classifier: Programming Language :: Python :: 3.4
Classifier: Programming Language :: Python :: 3.5
Classifier: Programming Language :: Python :: 3.6
Classifier: Programming Language :: Python :: 3.7
Classifier: Programming Language :: Python :: 3.8
Classifier: License :: OSI Approved :: GNU Lesser General Public License v3 or later (LGPLv3+)
Classifier: Topic :: Multimedia :: Graphics
Classifier: Operating System :: OS Independent
